[
    {
        "title": "SFX project",
        "text": "Check Marketing strategy ",
        "id": "sktwii0ukws380bd"
    },
    {
        "title": "Cross check Node.js task",
        "text": "Homework number 11 ",
        "id": "sktwii0ukws38jaj"
    },
    {
        "title": "Grocery shopping ",
        "text": "Eggs, Milk, Potatoes, tomato ",
        "id": "sktwii0ukws39dn3"
    },
    {
        "title": "House Cleaning ",
        "text": "Saturday ",
        "id": "sktwii0ukws3ap80"
    },
    {
        "title": "Hide dead body !",
        "text": "just kidding :) ",
        "id": "sktwii0ukws3bx3t"
    }
]